asymintervals/__init__.py
asymintervals/asymintervals.py
asymintervals/inspiration.py
asymintervals-1.2.0.dist-info/licenses/LICENSE
asymintervals-1.2.0.dist-info/METADATA
asymintervals-1.2.0.dist-info/WHEEL
asymintervals-1.2.0.dist-info/top_level.txt
asymintervals-1.2.0.dist-info/RECORD
