Metadata-Version: 2.4
Name: asymintervals
Version: 1.2.0
Summary: Python Library for Asymmetric Interval Numbers
Author-email: Wojciech Sałabun <w.salabun@il-pib.pl>
License-Expression: MIT
Project-URL: Homepage, https://github.com/wsalabun/asymintervals
Project-URL: Issues, https://github.com/wsalabun/asymintervals/-/issues
Classifier: Programming Language :: Python :: 3
Classifier: Operating System :: OS Independent
Requires-Python: >=3.11
License-File: LICENSE
Requires-Dist: numpy
Requires-Dist: matplotlib
Dynamic: license-file
